banquo/__init__.py
banquo/__main__.py
banquo/banquo.py
banquo/kernels.py
banquo/numpyro.py
banquo/py.typed
banquo-0.7.1.dist-info/LICENSE
banquo-0.7.1.dist-info/METADATA
banquo-0.7.1.dist-info/WHEEL
banquo-0.7.1.dist-info/entry_points.txt
banquo-0.7.1.dist-info/RECORD
