Metadata-Version: 2.3
Name: banquo
Version: 0.7.1
Summary: Banquo: a Python package for building Bayesian Nonparanormal models
License: MIT
Author: Luiz Desuó Neto
Author-email: luizdesuo@gmail.com
Requires-Python: >=3.11,<4.0
Classifier: Development Status :: 3 - Alpha
Classifier: License :: OSI Approved :: MIT License
Classifier: Programming Language :: Python :: 3
Classifier: Programming Language :: Python :: 3.11
Classifier: Programming Language :: Python :: 3.12
Classifier: Programming Language :: Python :: 3.13
Requires-Dist: array-api-compat (>=1.9)
Requires-Dist: click (>=8.1.7)
Requires-Dist: numpyro[cpu,gpu] (>=0.13.2)
Project-URL: Changelog, https://github.com/luizdesuo/banquo/releases
Project-URL: Homepage, https://github.com/luizdesuo/banquo
Project-URL: Repository, https://github.com/luizdesuo/banquo
